---
25layout:     post
title:      java中的动态绑定技术
subtitle:   动态绑定
date:       2019-01-21
author:     rosewind
header-img: img/animation/640.jpg
catalog: true
tags:
    - java
---

# 前言

学习《java编程思想》，看了动态绑定和多态这一章节。博客上的资料比较散，故总结一下这个问题。

# 动态绑定与静态绑定

##  静态绑定

这是一个方法重载的实例，在编译阶段就可以确定，调用的是以String为参数的方法

```java
public class TestMain {
  public static void main(String[] args) {
      String str = new String();
      Caller caller = new Caller();
      caller.call(str);
  }

  static class Caller {
      public void call(Object obj) {
          System.out.println("an Object instance in Caller");
      }
      
      public void call(String str) {
          System.out.println("a String instance in in Caller");
      }
  }
}
```

执行结果:

```java
a String instance in in Caller
```

为了验证确实是静态绑定，用javap命令反编译，结果如下:

```java
22:19 $ javap -c TestMain
Compiled from "TestMain.java"
public class TestMain {
  public TestMain();
    Code:
       0: aload_0
       1: invokespecial #1                  // Method java/lang/Object."<init>":()V
       4: return

  public static void main(java.lang.String[]);
    Code:
       0: new           #2                  // class java/lang/String
       3: dup
       4: invokespecial #3                  // Method java/lang/String."<init>":()V
       7: astore_1
       8: new           #4                  // class TestMain$Caller
      11: dup
      12: invokespecial #5                  // Method TestMain$Caller."<init>":()V
      15: astore_2
      16: aload_2
      17: aload_1
      18: invokevirtual #6                  // Method TestMain$Caller.call:(Ljava/lang/String;)V
      21: return
}
```

根据第18行，可以看出，确实是静态绑定

## 动态绑定

```java
public class TestMain {
  public static void main(String[] args) {
      String str = new String();
      Caller caller = new SubCaller();
      caller.call(str);
  }
  
  static class Caller {
      public void call(String str) {
          System.out.println("a String instance in Caller");
      }
  }
  
  static class SubCaller extends Caller {
      @Override
      public void call(String str) {
          System.out.println("a String instance in SubCaller");
      }
  }
}
```

运行结果如下:

```java
a String instance in SubCaller
```

根据结果可以看出，其调用了SubCaller的call方法实现，而非Caller的call方法。这一结果的产生的原因是因为在运行时发生了动态绑定，在绑定过程中需要确定调用哪个版本的call方法实现。

同样用javap查看:

```java
public class TestMain {
  public TestMain();
    Code:
       0: aload_0
       1: invokespecial #1                  // Method java/lang/Object."<init>":()V
       4: return

  public static void main(java.lang.String[]);
    Code:
       0: new           #2                  // class java/lang/String
       3: dup
       4: invokespecial #3                  // Method java/lang/String."<init>":()V
       7: astore_1
       8: new           #4                  // class TestMain$SubCaller
      11: dup
      12: invokespecial #5                  // Method TestMain$SubCaller."<init>":()V
      15: astore_2
      16: aload_2
      17: aload_1
      18: invokevirtual #6                  // Method TestMain$Caller.call:(Ljava/lang/String;)V
      21: return
}
```

根据18行，在编译阶段还是Caller.call,而运行结果显示调用的是SubCaller.call,说明在运行时，发生了动态绑定

## 区别

- 静态绑定在编译时期，动态绑定在运行时期
- 静态绑定只用到类型信息，方法的解析根据引用变量的类型决定，而动态绑定则根据实际引用的的对象决定
- 在java中，private static 和 final 方法都是静态绑定
- 多态是通过动态绑定实现的,而方法重载是静态绑定

## 动态绑定的机制

在JVM加载类的同时，会在方法区中为这个类存放很多信息(详见《[Java 虚拟机体系结构](http://link.zhihu.com/?target=http%3A//hxraid.iteye.com/blog/676235) 》)。其中就有一个数据结构叫方法表。它以数组的形式记录了当前类及其所有超类的可见方法字节码在内存中的直接地址 。

以Integer类为例，初始时，表都是空的。运行时，方法表从最顶层的超类中，添加方法。首先是Object类中的一些方法

| 方法名          | 地址 | 注释                           |
| --------------- | ---- | ------------------------------ |
| Object.toString | 111  | Object.toString method address |
| ...             | ...  | 其他的10个方法                 |

接下来加载下一层的超类的方法，若已经存在，就修改地址。这里加入的是Number类的方法

| 方法名          | 地址 | 注释                           |
| --------------- | ---- | ------------------------------ |
| Object.toString | 111  | Number.toString method address |
| Number.intValue | 222  | Number.intValue method address |
| ...             | ...  |                                |

**这里toString的地址还没有改变，因为Number类并没有重写toString**

[Number类](https://docs.oracle.com/javase/7/docs/api/java/lang/Number.html)

不断地向方法表中加入

****

| 方法名           | 地址 | 注释                             |
| ---------------- | ---- | -------------------------------- |
| Object.toString  | 333  | Integer.toString method address  |
| Number.intValue  | 444  | interger.intValue method address |
| Integer.parseInt | 555  | Number.longValue method address  |
| ...              | ...  | 其他一些方法                     |

****

**这里toString的地址变了，因为Integer重写了这个方法，但是方法名不会变**

[Integer类](https://docs.oracle.com/javase/7/docs/api/java/lang/Integer.html)

注意:

- 在`Caller caller = new SubCaller();`时，声明为Caller类型，会检查Caller中的方法subCaller是不是都有，若Caller方法表中有f(),而subCaller中没有，编译不会通过
- 动态绑定即通过动态创建的对象的方法表来定位方法，即调用`caller.call(str);`时